{
  "cli": {
    "version": ">= 13.2.3",
    "appVersionSource": "remote"
  },
  "build": {
    "development": {
      "developmentClient": true,
      "distribution": "internal",
      "node": "22.21.0",
      "pnpm": "10.19.0",
      "ios": {
        "simulator": true
      },
      "android": {
        "buildType": "apk"
      }
    },
    "preview": {
      "distribution": "internal",
      "ios": {
        "simulator": false
      },
      "android": {
        "buildType": "apk"
      }
    },
    "production": {
      "ios": {
        "simulator": false
      },
      "android": {
        "buildType": "app-bundle"
      }
    }
  },
  "submit": {
    "production": {}
  }
}
